aws_msk_iam_sasl_signer/MSKAuthTokenProvider.py
aws_msk_iam_sasl_signer/__init__.py
aws_msk_iam_sasl_signer/cli.py
tests/__init__.py
tests/test_auth_token_provider.py
aws_msk_iam_sasl_signer_python-1.0.0.dist-info/LICENSE
aws_msk_iam_sasl_signer_python-1.0.0.dist-info/METADATA
aws_msk_iam_sasl_signer_python-1.0.0.dist-info/WHEEL
aws_msk_iam_sasl_signer_python-1.0.0.dist-info/entry_points.txt
aws_msk_iam_sasl_signer_python-1.0.0.dist-info/top_level.txt
aws_msk_iam_sasl_signer_python-1.0.0.dist-info/RECORD
