Metadata-Version: 2.1
Name: aws-msk-iam-sasl-signer-python
Version: 1.0.0
Summary: Amazon MSK Library in Python for SASL/OAUTHBEARER Auth
Home-page: https://github.com/aws/aws-msk-iam-sasl-signer-python
Author: Amazon Managed Streaming for Apache Kafka
License: Apache Software License 2.0
Keywords: aws-msk-iam-sasl-signer-python
Classifier: Development Status :: 5 - Production/Stable
Classifier: Intended Audience :: Developers
Classifier: License :: OSI Approved :: Apache Software License
Classifier: Natural Language :: English
Classifier: Programming Language :: Python :: 3.8
Classifier: Programming Language :: Python :: 3.9
Classifier: Programming Language :: Python :: 3.10
Classifier: Programming Language :: Python :: 3.11
Requires-Python: >=3.8
License-File: LICENSE
Requires-Dist: Click >=7.0
Requires-Dist: boto3 ==1.26.125
Requires-Dist: botocore ==1.29.125
